store_dir_content/__init__.py
store_dir_content/cli.py
store_dir_content-0.1.dist-info/METADATA
store_dir_content-0.1.dist-info/WHEEL
store_dir_content-0.1.dist-info/entry_points.txt
store_dir_content-0.1.dist-info/top_level.txt
store_dir_content-0.1.dist-info/RECORD
