Metadata-Version: 2.1
Name: store_dir_content
Version: 0.1
Summary: A CLI tool to read files and extract content based on extensions.
Home-page: https://github.com/lukasramroth/store_dir_content
Author: Lukas Ramroth
Author-email: 
Classifier: Programming Language :: Python :: 3
Classifier: License :: OSI Approved :: MIT License
Classifier: Operating System :: OS Independent
Requires-Python: >=3.6
Requires-Dist: pathspec
